{"cameraMode":{"drawMode":0,"name":"Shaded","section":"Shading Mode"},"sceneLighting":true,"audioPlay":false,"sceneViewState":{"m_AlwaysRefresh":false,"showFog":true,"showSkybox":true,"showFlares":true,"showImageEffects":true,"showParticleSystems":true,"showVisualEffectGraphs":true,"m_FxEnabled":true},"in2DMode":false,"pivot":{"x":0.8999999165534973,"y":-274.6247863769531,"z":85.8681411743164},"rotation":{"x":-0.10056759417057038,"y":0.6691575050354004,"z":-0.09212280064821243,"w":-0.730502724647522},"size":2.2524001598358156,"orthographic":false}